CHANGELOG.txt
LICENCE.txt
MANIFEST.in
README.txt
Upload_Help.txt
setup.py
Mustraxlib/__init__.py
Mustraxlib.egg-info/PKG-INFO
Mustraxlib.egg-info/SOURCES.txt
Mustraxlib.egg-info/dependency_links.txt
Mustraxlib.egg-info/requires.txt
Mustraxlib.egg-info/top_level.txt