Metadata-Version: 2.1
Name: Mustraxlib
Version: 2.0.7
Summary: Simple tools for convenient programming
Home-page: 
Author: Programmer101
Author-email: wsl.com.uk@gmail.com
License: Copyright 2023 Programmer101. All rights reserved. See LICENCE.txt for details
Keywords: Efficiency,User Input,Hashing,Encryption,Matrix,2D Lists,List Manipulation
Classifier: Development Status :: 5 - Production/Stable
Classifier: Intended Audience :: Education
Classifier: Operating System :: Microsoft :: Windows :: Windows 11
Classifier: License :: Other/Proprietary License
Classifier: Programming Language :: Python :: 3.12
License-File: LICENCE.txt
